{
  "$schema": "https://schema.tauri.app/config/2",
  "productName": "ORNAS",
  "version": "0.9.0-beta",
  "identifier": "io.ornas",
  "build": {
    "beforeDevCommand": "npm run dev",
    "devUrl": "http://localhost:1420",
    "beforeBuildCommand": "npm run build",
    "frontendDist": "../dist"
  },
  "app": {
    "windows": [
      {
        "label": "main",
        "title": "ORNAS",
        "width": 1100,
        "height": 700,
        "minWidth": 800,
        "minHeight": 500,
        "center": true,
        "decorations": true,
        "resizable": true
      }
    ],
    "security": {
      "csp": "default-src 'self'; img-src 'self' asset: https://asset.localhost; style-src 'self' 'unsafe-inline'; font-src 'self'"
    },
    "trayIcon": {
      "iconPath": "icons/32x32.png",
      "iconAsTemplate": true
    }
  },
  "bundle": {
    "active": true,
    "targets": "all",
    "icon": [
      "icons/32x32.png",
      "icons/128x128.png",
      "icons/128x128@2x.png",
      "icons/icon.icns",
      "icons/icon.ico"
    ]
  }
}
